stopwatch.v
module stopwatch(
    input clk,
    input reset,
    input start,
    input stop,
    output reg [5:0] seconds,
    output reg [5:0] minutes,
    output reg run
);
reg [25:0] divider;
reg tick;
always @(posedge clk) begin
    if (divider == 9) begin
        divider <= 0;
        tick <= 1;
    end else begin
        divider <= divider + 1;
        tick <= 0;
    end
end
always @(posedge clk) begin
    if (reset) begin
        run <= 0;
    end else begin
        if (start) run <= 1;
        if (stop)  run <= 0;
    end
end
always @(posedge clk) begin
    if (reset) begin
        seconds <= 0;
        minutes <= 0;
    end else if (tick && run) begin
        if (seconds == 59) begin
            seconds <= 0;
            if (minutes == 59) minutes <= 0;
            else minutes <= minutes + 1;
        end else begin
            seconds <= seconds + 1;
        end
    end
end
endmodule

tb_stopwatch.v
`timescale 1ns/1ps
module tb_stopwatch;
reg clk;
reg reset;
reg start;
reg stop;
wire [5:0] seconds;
wire [5:0] minutes;
wire run;
stopwatch DUT(
    .clk(clk),
    .reset(reset),
    .start(start),
    .stop(stop),
    .seconds(seconds),
    .minutes(minutes),
    .run(run)
);
initial begin
    clk = 0;
    forever #5 clk = ~clk;
end
initial begin
    reset = 1; start = 0; stop = 0;
    #20 reset = 0;
    #30 start = 1; #10 start = 0;
    #300 stop = 1; #10 stop = 0;
    #200 start = 1; #10 start = 0;
    #300 reset = 1; #20 reset = 0;
    #200 $finish;
end
initial begin
    $dumpfile("stopwatch.vcd");
    $dumpvars(0, tb_stopwatch);
end
endmodule

stopwatch.vcd
$date
	Thu Nov 13 22:42:22 2025
$end
$version
	Icarus Verilog
$end
$timescale
	1ps
$end
$scope module tb_stopwatch $end
$var wire 6 ! seconds [5:0] $end
$var wire 1 " run $end
$var wire 6 # minutes [5:0] $end
$var reg 1 $ clk $end
$var reg 1 % reset $end
$var reg 1 & start $end
$var reg 1 ' stop $end
$scope module DUT $end
$var wire 1 $ clk $end
$var wire 1 % reset $end
$var wire 1 & start $end
$var wire 1 ' stop $end
$var reg 26 ( divider [25:0] $end
$var reg 6 ) minutes [5:0] $end
$var reg 1 " run $end
$var reg 6 * seconds [5:0] $end
$var reg 1 + tick $end
$upscope $end
$upscope $end
$enddefinitions $end
#0
$dumpvars
x+
bx *
bx )
bx (
0'
0&
1%
0$
bx #
x"
bx !
$end
#5000
0+
0"
b0 #
b0 )
b0 !
b0 *
1$
#10000
0$
#15000
1$
#20000
0$
0%
#25000
1$
#30000
0$
#35000
1$
#40000
0$
#45000
1$
#50000
0$
1&
#55000
1"
1$
#60000
0$
0&
#65000
1$
#70000
0$
#75000
1$
#80000
0$
#85000
1$
#90000
0$
#95000
1$
#100000
0$
#105000
1$
#110000
0$
#115000
1$
#120000
0$
#125000
1$
#130000
0$
#135000
1$
#140000
0$
#145000
1$
#150000
0$
#155000
1$
#160000
0$
#165000
1$
#170000
0$
#175000
1$
#180000
0$
#185000
1$
#190000
0$
#195000
1$
#200000
0$
#205000
1$
#210000
0$
#215000
1$
#220000
0$
#225000
1$
#230000
0$
#235000
1$
#240000
0$
#245000
1$
#250000
0$
#255000
1$
#260000
0$
#265000
1$
#270000
0$
#275000
1$
#280000
0$
#285000
1$
#290000
0$
#295000
1$
#300000
0$
#305000
1$
#310000
0$
#315000
1$
#320000
0$
#325000
1$
#330000
0$
#335000
1$
#340000
0$
#345000
1$
#350000
0$
#355000
1$
#360000
0$
1'
#365000
0"
1$
#370000
0$
0'
#375000
1$
#380000
0$
#385000
1$
#390000
0$
#395000
1$
#400000
0$
#405000
1$
#410000
0$
#415000
1$
#420000
0$
#425000
1$
#430000
0$
#435000
1$
#440000
0$
#445000
1$
#450000
0$
#455000
1$
#460000
0$
#465000
1$
#470000
0$
#475000
1$
#480000
0$
#485000
1$
#490000
0$
#495000
1$
#500000
0$
#505000
1$
#510000
0$
#515000
1$
#520000
0$
#525000
1$
#530000
0$
#535000
1$
#540000
0$
#545000
1$
#550000
0$
#555000
1$
#560000
0$
#565000
1$
#570000
0$
1&
#575000
1"
1$
#580000
0$
0&
